Workbook

Sheet Допущения
A1: Допущения модели (жёлтые ячейки можно менять)
A2: Итоговая выручка — на 12-й месяц (стационарный срез). Всё, кроме пометки «факт», — допущение до Discovery и выбора LLM.
A4: Параметр | B4: Консервативно | C4: Базово | D4: Оптимистично | E4: Ед. | F4: Статус / источник
A5: Аудитория (факты и оценки)
A6: Аудитория Почты Mail | B6: 43000000 | C6: 51000000 | D6: 51000000 | E6: чел./мес | F6: 51 млн — Mediascope, дек. 2022 (факт, устарел); 43 млн ≈ 105 млн пользователей почты в РФ × 40,7% (inclient.ru, вторичный источник)
A7: Доля Mail среди почтовых ящиков специалистов/студентов/предпринимателей | B7: 0.24 | C7: 0.35 | D7: 0.4 | E7: % | F7: 24% — опрос Яндекс 360 (апр. 2026, города-миллионники); 40% — доля Mail в РФ (inclient.ru)
A8: Доля, активная в MAX/VK (можно достучаться ботом) | B8: 0.6 | C8: 0.7 | D8: 0.8 | E8: % | F8: допущение; MAX 85 млн ежедневно (май 2026, VK) при ~105 млн пользователей почты
A9: Студенты вузов | B9: 4846085 | C9: 4846085 | D9: 4846085 | E9: чел. | F9: факт: Минобрнауки, 2025/26 (СПО не включены)
A10: Занятые в экономике | B10: 74600000 | C10: 74600000 | D10: 74600000 | E10: чел. | F10: факт: Росстат, март 2026
A11: Доля специалистов (работа с почтой и перепиской) среди занятых | B11: 0.25 | C11: 0.3 | D11: 0.35 | E11: % | F11: допущение; проверить по данным Росстата/HH
A12: Предприниматели: самозанятые и ИП | B12: 20400000 | C12: 20400000 | D12: 20400000 | E12: чел. | F12: факт: ФНС, апрель 2026: 16,41 млн НПД + 4,84 млн ИП − 0,84 млн ИП на НПД
A13: Справка: юрлиц в России (команды) | B13: 3139085 | C13: 3139085 | D13: 3139085 | E13: шт. | F13: факт: ФНС, апрель 2026; команды вне расчёта 1-го года (H8 после MVP)
A14: Воронка (общая)
A15: Охват: узнали о боте за 12 мес. (от активных в мессенджере) | B15: 0.1 | C15: 0.25 | D15: 0.4 | E15: % | F15: допущение; VK владеет и Почтой, и MAX → кросс-промо; главный рычаг, проверять пилотом
A16: Множитель доли подключения (сценарий) | B16: 0.5 | C16: 1 | D16: 1.5 | E16: × | F16: допущение; масштабирует доли подключения ниже
A17: Множитель конверсии в оплату (сценарий) | B17: 0.5 | C17: 1 | D17: 1.5 | E17: × | F17: допущение; ориентиры: платят за ИИ 12% (ICT.Moscow, 03.2026), готовы платить 10% (OMI, 05.2026), 55% среди пользователей ИИ (ComNews, 06.2026)
A18: Воронка по сегментам (базовые значения)
A19: Личные: подключили ящик (от охваченных) | B19: 0.03 | C19: 0.03 | D19: 0.03 | E19: % | F19: допущение
A20: Личные: платят (от подключивших) | B20: 0.03 | C20: 0.03 | D20: 0.03 | E20: % | F20: допущение
A21: Личные: цена | B21: 149 | C21: 149 | D21: 149 | E21: ₽/мес | F21: допущение; ориентир Алиса Про 250 ₽/мес
A22: Студенты: подключили | B22: 0.05 | C22: 0.05 | D22: 0.05 | E22: % | F22: допущение
A23: Студенты: платят | B23: 0.04 | C23: 0.04 | D23: 0.04 | E23: % | F23: допущение; молодёжь готова платить больше (3 493 ₽/мес, 18–24 г., ComNews)
A24: Студенты: цена | B24: 99 | C24: 99 | D24: 99 | E24: ₽/мес | F24: допущение
A25: Специалисты: подключили | B25: 0.08 | C25: 0.08 | D25: 0.08 | E25: % | F25: допущение
A26: Специалисты: платят | B26: 0.08 | C26: 0.08 | D26: 0.08 | E26: % | F26: допущение
A27: Специалисты: цена | B27: 199 | C27: 199 | D27: 199 | E27: ₽/мес | F27: допущение
A28: Предприниматели: подключили | B28: 0.1 | C28: 0.1 | D28: 0.1 | E28: % | F28: допущение
A29: Предприниматели: платят | B29: 0.12 | C29: 0.12 | D29: 0.12 | E29: % | F29: допущение
A30: Предприниматели: цена | B30: 299 | C30: 299 | D30: 299 | E30: ₽/мес | F30: допущение
A31: Использование LLM (на пользователя в месяц)
A32: Сводок в месяц | B32: 30 | C32: 30 | D32: 30 | E32: шт. | F32: допущение (S1 ежедневно)
A33: Токенов на сводку (вход + выход) | B33: 11000 | C33: 11000 | D33: 11000 | E33: ток. | F33: допущение (~20 писем × 500 + ответ)
A34: Прочих запросов в месяц (поиск, пересказ, черновик) | B34: 20 | C34: 20 | D34: 20 | E34: шт. | F34: допущение; для сравнения: активные пользователи ИИ обращаются ~17 раз/мес (Авито Работа)
A35: Токенов на прочий запрос (вход + выход) | B35: 8600 | C35: 8600 | D35: 8600 | E35: ток. | F35: допущение
A36: Нагрузка бесплатных подключивших относительно платящих | B36: 0.25 | C36: 0.15 | D36: 0.1 | E36: % | F36: допущение; задаётся лимитами бесплатного тарифа
A37: Цена LLM по API (смесь моделей) | B37: 300 | C37: 130 | D37: 65 | E37: ₽ за 1 млн ток. | F37: GigaChat Lite 65 ₽, GigaChat Pro 500 ₽, YandexGPT Lite 200 ₽, Pro 800 ₽ за 1 млн (РБК/Nodul, авг. 2026); смесь ~85% Lite + 15% Pro; уточнить после выбора LLM
A38: LLM на своём железе (Qwen и др. открытые модели)
A39: Аренда одного GPU-сервера | B39: 410000 | C39: 80000 | D39: 35000 | E39: ₽/мес | F39: cons: H100 80 ГБ (Cloud.ru 9,5 ₽/мин ≈ 410 тыс.), Qwen3-32B; base: A100 80 ГБ 80 тыс. (Selectel), модель 14B-класса; opt: RTX 4090 ≈ 35 тыс. (Timeweb), Qwen3-8B
A40: Пропускная способность одного GPU | B40: 1800 | C40: 3000 | D40: 1700 | E40: ток./с | F40: допущение по бенчмаркам: Qwen3-32B на H100 ≈ 2 350 ток./с (GPUStack, vLLM), Qwen3-8B на A10 ≈ 850 ток./с (TrueFoundry); длинные входы (сводка) снижают
A41: GigaChat3.1 Lightning (10B-A1.8B, MoE): аренда GPU-сервера | B41: 410000 | C41: 80000 | D41: 35000 | E41: ₽/мес | F41: те же GPU, что выше: H100 / A100 80 ГБ / RTX 4090; веса fp8 ≈ 10 ГБ, влезают в любую; лицензия MIT
A42: GigaChat3.1 Lightning: пропускная способность одного GPU | B42: 5300 | C42: 2200 | D42: 1600 | E42: ток./с | F42: опора: 6 883 ток./с (вход+выход) на H100, fp8, concurrency 32 (карточка ai-sage/GigaChat3.1-10B-A1.8B) −23% на длинные входы, как у Qwen; A100 (нет fp8) ≈ 0,5× H100, 4090 ≈ 0,3× — мои допущения, замерить
A43: Средняя загрузка GPU | B43: 0.25 | C43: 0.3 | D43: 0.3 | E43: % | F43: допущение: пики нагрузки утром, ночью простой
A44: Запас на отказоустойчивость и пики | B44: 1.3 | C44: 1.3 | D44: 1.3 | E44: × | F44: допущение
A45: MLOps-инженер для своей инфраструктуры | B45: 150000 | C45: 150000 | D45: 150000 | E45: ₽/мес | F45: допущение (~0,5 ставки)
A46: Расходы
A47: Хостинг в РФ, БД, очереди (постоянно) | B47: 50000 | C47: 50000 | D47: 50000 | E47: ₽/мес | F47: допущение
A48: Инфраструктура на одного подключившего | B48: 1.5 | C48: 1 | D48: 0.7 | E48: ₽/мес | F48: допущение (хранение токенов, опрос IMAP)
A49: Юрист и документы по 152-ФЗ (разово) | B49: 500000 | C49: 500000 | D49: 500000 | E49: ₽ | F49: допущение; амортизируем на 12 мес.
A50: Команда разработки и поддержки | B50: 300000 | C50: 300000 | D50: 300000 | E50: ₽/мес | F50: допущение (~3 человека); для «без учёта труда» обнулить
A51: Привлечение одного подключившего | B51: 60 | C51: 30 | D51: 15 | E51: ₽ | F51: допущение; собственные каналы VK (баннеры в Почте и MAX)
A52: Комиссия платёжного сервиса | B52: 0.05 | C52: 0.05 | D52: 0.05 | E52: % | F52: допущение
A53: Налоги с выручки | B53: 0.06 | C53: 0.06 | D53: 0.06 | E53: % | F53: допущение (УСН 6% с доходов; для юрлица уточнить)

Sheet Расчёт
A1: Расчёт эффектов (формулы, пересчитываются от листа «Допущения»)
A3: Показатель | B3: Консервативно | C3: Базово | D3: Оптимистично | E3: Ед. | F3: Как считается
A4: Аудитория (потенциал)
A5: Студенты на Mail | B5: =Допущения!B9*Допущения!B7 | C5: =Допущения!C9*Допущения!C7 | D5: =Допущения!D9*Допущения!D7 | E5: чел. | F5: студенты × доля Mail
A6: Специалисты на Mail | B6: =Допущения!B10*Допущения!B11*Допущения!B7 | C6: =Допущения!C10*Допущения!C11*Допущения!C7 | D6: =Допущения!D10*Допущения!D11*Допущения!D7 | E6: чел. | F6: занятые × доля специалистов × доля Mail
A7: Предприниматели на Mail | B7: =Допущения!B12*Допущения!B7 | C7: =Допущения!C12*Допущения!C7 | D7: =Допущения!D12*Допущения!D7 | E7: чел. | F7: самозанятые и ИП × доля Mail
A8: Личные пользователи на Mail | B8: =MAX(0,Допущения!B6-B5-B6-B7) | C8: =MAX(0,Допущения!C6-C5-C6-C7) | D8: =MAX(0,Допущения!D6-D5-D6-D7) | E8: чел. | F8: аудитория Mail за вычетом трёх сегментов (пересечения учтены вычитанием)
A9: Аудитория Mail всего (TAM) | B9: =B8+B5+B6+B7 | C9: =C8+C5+C6+C7 | D9: =D8+D5+D6+D7 | E9: чел.
A10: Из них активны в MAX/VK (SAM) | B10: =B9*Допущения!B8 | C10: =C9*Допущения!C8 | D10: =D9*Допущения!D8 | E10: чел. | F10: TAM × доля активных в мессенджере
A11: Воронка за 12 месяцев
A12: Охвачено (узнали о боте) | B12: =B10*Допущения!B15 | C12: =C10*Допущения!C15 | D12: =D10*Допущения!D15 | E12: чел. | F12: SAM × охват
A13: Подключили: Личные | B13: =B8*Допущения!B8*Допущения!B15*Допущения!B19*Допущения!B16 | C13: =C8*Допущения!C8*Допущения!C15*Допущения!C19*Допущения!C16 | D13: =D8*Допущения!D8*Допущения!D15*Допущения!D19*Допущения!D16 | E13: чел. | F13: аудитория сегмента × активные × охват × подключение × множитель
A14: Платят: Личные | B14: =B13*Допущения!B20*Допущения!B17 | C14: =C13*Допущения!C20*Допущения!C17 | D14: =D13*Допущения!D20*Допущения!D17 | E14: чел. | F14: подключившие × конверсия в оплату × множитель
A15: Подключили: Студенты | B15: =B5*Допущения!B8*Допущения!B15*Допущения!B22*Допущения!B16 | C15: =C5*Допущения!C8*Допущения!C15*Допущения!C22*Допущения!C16 | D15: =D5*Допущения!D8*Допущения!D15*Допущения!D22*Допущения!D16 | E15: чел. | F15: аудитория сегмента × активные × охват × подключение × множитель
A16: Платят: Студенты | B16: =B15*Допущения!B23*Допущения!B17 | C16: =C15*Допущения!C23*Допущения!C17 | D16: =D15*Допущения!D23*Допущения!D17 | E16: чел. | F16: подключившие × конверсия в оплату × множитель
A17: Подключили: Специалисты | B17: =B6*Допущения!B8*Допущения!B15*Допущения!B25*Допущения!B16 | C17: =C6*Допущения!C8*Допущения!C15*Допущения!C25*Допущения!C16 | D17: =D6*Допущения!D8*Допущения!D15*Допущения!D25*Допущения!D16 | E17: чел. | F17: аудитория сегмента × активные × охват × подключение × множитель
A18: Платят: Специалисты | B18: =B17*Допущения!B26*Допущения!B17 | C18: =C17*Допущения!C26*Допущения!C17 | D18: =D17*Допущения!D26*Допущения!D17 | E18: чел. | F18: подключившие × конверсия в оплату × множитель
A19: Подключили: Предприниматели/самозанятые | B19: =B7*Допущения!B8*Допущения!B15*Допущения!B28*Допущения!B16 | C19: =C7*Допущения!C8*Допущения!C15*Допущения!C28*Допущения!C16 | D19: =D7*Допущения!D8*Допущения!D15*Допущения!D28*Допущения!D16 | E19: чел. | F19: аудитория сегмента × активные × охват × подключение × множитель
A20: Платят: Предприниматели/самозанятые | B20: =B19*Допущения!B29*Допущения!B17 | C20: =C19*Допущения!C29*Допущения!C17 | D20: =D19*Допущения!D29*Допущения!D17 | E20: чел. | F20: подключившие × конверсия в оплату × множитель
A21: Подключили ящик, всего | B21: =B13+B15+B17+B19 | C21: =C13+C15+C17+C19 | D21: =D13+D15+D17+D19 | E21: чел.
A22: Платящие, всего (SOM) | B22: =B14+B16+B18+B20 | C22: =C14+C16+C18+C20 | D22: =D14+D16+D18+D20 | E22: чел.
A23: Подключили, но не платят | B23: =B21-B22 | C23: =C21-C22 | D23: =D21-D22 | E23: чел.
A24: Сквозная конверсия: платящие ÷ SAM | B24: =B22/B10 | C24: =C22/C10 | D24: =D22/D10 | E24: %
A25: Выручка
A26: Выручка: Личные | B26: =B14*Допущения!B21 | C26: =C14*Допущения!C21 | D26: =D14*Допущения!D21 | E26: ₽/мес | F26: платящие × цена
A27: Выручка: Студенты | B27: =B16*Допущения!B24 | C27: =C16*Допущения!C24 | D27: =D16*Допущения!D24 | E27: ₽/мес | F27: платящие × цена
A28: Выручка: Специалисты | B28: =B18*Допущения!B27 | C28: =C18*Допущения!C27 | D28: =D18*Допущения!D27 | E28: ₽/мес | F28: платящие × цена
A29: Выручка: Предприниматели/самозанятые | B29: =B20*Допущения!B30 | C29: =C20*Допущения!C30 | D29: =D20*Допущения!D30 | E29: ₽/мес | F29: платящие × цена
A30: Выручка, ₽/мес (к концу 1-го года) | B30: =B26+B27+B28+B29 | C30: =C26+C27+C28+C29 | D30: =D26+D27+D28+D29 | E30: ₽/мес
A31: Выручка в годовом выражении | B31: =B30*12 | C31: =C30*12 | D31: =D30*12 | E31: ₽/год | F31: месячная × 12
A32: Потенциал при 100% охвате, ₽/мес | B32: =B8*Допущения!B8*Допущения!B19*Допущения!B16*Допущения!B20*Допущения!B17*Допущения!B21+B5*Допущения!B8*Допущения!B22*Допущения!B16*Допущения!B23*Допущения!B17*Допущения!B24+B6*Допущения!B8*Допущения!B25*Допущения!B16*Допущения!B26*Допущения!B17*Допущения!B27+B7*Допущения!B8*Допущения!B28*Допущения!B16*Допущения!B29*Допущения!B17*Допущения!B30 | C32: =C8*Допущения!C8*Допущения!C19*Допущения!C16*Допущения!C20*Допущения!C17*Допущения!C21+C5*Допущения!C8*Допущения!C22*Допущения!C16*Допущения!C23*Допущения!C17*Допущения!C24+C6*Допущения!C8*Допущения!C25*Допущения!C16*Допущения!C26*Допущения!C17*Допущения!C27+C7*Допущения!C8*Допущения!C28*Допущения!C16*Допущения!C29*Допущения!C17*Допущения!C30 | D32: =D8*Допущения!D8*Допущения!D19*Допущения!D16*Допущения!D20*Допущения!D17*Допущения!D21+D5*Допущения!D8*Допущения!D22*Допущения!D16*Допущения!D23*Допущения!D17*Допущения!D24+D6*Допущения!D8*Допущения!D25*Допущения!D16*Допущения!D26*Допущения!D17*Допущения!D27+D7*Допущения!D8*Допущения!D28*Допущения!D16*Допущения!D29*Допущения!D17*Допущения!D30 | E32: ₽/мес | F32: верхняя граница: если бы о боте узнали все активные
A33: Себестоимость LLM: API и своё железо
A34: Токенов на одного активного в месяц | B34: =Допущения!B32*Допущения!B33+Допущения!B34*Допущения!B35 | C34: =Допущения!C32*Допущения!C33+Допущения!C34*Допущения!C35 | D34: =Допущения!D32*Допущения!D33+Допущения!D34*Допущения!D35 | E34: ток. | F34: сводки + прочие запросы
A35: Нагрузка в «платящих-эквивалентах» | B35: =B22+B23*Допущения!B36 | C35: =C22+C23*Допущения!C36 | D35: =D22+D23*Допущения!D36 | E35: чел. | F35: платящие + бесплатные × их нагрузка
A36: Токенов в месяц всего, млрд | B36: =B35*B34/1000000000 | C36: =C35*C34/1000000000 | D36: =D35*D34/1000000000 | E36: млрд
A37: LLM по API, ₽/мес | B37: =B35*B34*Допущения!B37/1000000 | C37: =C35*C34*Допущения!C37/1000000 | D37: =D35*D34*Допущения!D37/1000000 | E37: ₽/мес | F37: токены × цена за 1 млн
A38: Нужно GPU (со своим железом) | B38: =ROUNDUP(B35*B34*Допущения!B44/(Допущения!B40*2592000*Допущения!B43),0) | C38: =ROUNDUP(C35*C34*Допущения!C44/(Допущения!C40*2592000*Допущения!C43),0) | D38: =ROUNDUP(D35*D34*Допущения!D44/(Допущения!D40*2592000*Допущения!D43),0) | E38: шт. | F38: токены × запас ÷ (пропускная × секунд в месяце × загрузка)
A39: LLM на своём железе, ₽/мес | B39: =B38*Допущения!B39+Допущения!B45 | C39: =C38*Допущения!C39+Допущения!C45 | D39: =D38*Допущения!D39+Допущения!D45 | E39: ₽/мес | F39: GPU + MLOps
A40: Нужно GPU (Lightning) | B40: =ROUNDUP(B35*B34*Допущения!B44/(Допущения!B42*2592000*Допущения!B43),0) | C40: =ROUNDUP(C35*C34*Допущения!C44/(Допущения!C42*2592000*Допущения!C43),0) | D40: =ROUNDUP(D35*D34*Допущения!D44/(Допущения!D42*2592000*Допущения!D43),0) | E40: шт. | F40: как для Qwen, но с пропускной способностью Lightning
A41: LLM на своём железе: Lightning, ₽/мес | B41: =B40*Допущения!B41+Допущения!B45 | C41: =C40*Допущения!C41+Допущения!C45 | D41: =D40*Допущения!D41+Допущения!D45 | E41: ₽/мес | F41: GPU + MLOps; качество ниже 14B (по замерам Сбера ≈ Qwen3-4B), проверить в тесте сценариев
A42: Эффективная цена токена, Lightning, ₽ за 1 млн | B42: =B41*1000000/(B35*B34) | C42: =C41*1000000/(C35*C34) | D42: =D41*1000000/(D35*D34) | E42: ₽ | F42: для сравнения с API и Qwen
A43: Эффективная цена токена на своём железе, ₽ за 1 млн | B43: =B39*1000000/(B35*B34) | C43: =C39*1000000/(C35*C34) | D43: =D39*1000000/(D35*D34) | E43: ₽ | F43: для сравнения с API
A44: Прочие расходы, ₽/мес
A45: Инфраструктура на пользователей | B45: =B21*Допущения!B48 | C45: =C21*Допущения!C48 | D45: =D21*Допущения!D48 | E45: ₽/мес
A46: Привлечение (в среднем за год) | B46: =B21*Допущения!B51/12 | C46: =C21*Допущения!C51/12 | D46: =D21*Допущения!D51/12 | E46: ₽/мес | F46: подключившие × CAC ÷ 12
A47: Комиссия платёжного сервиса | B47: =B30*Допущения!B52 | C47: =C30*Допущения!C52 | D47: =D30*Допущения!D52 | E47: ₽/мес
A48: Налоги | B48: =B30*Допущения!B53 | C48: =C30*Допущения!C53 | D48: =D30*Допущения!D53 | E48: ₽/мес
A49: Постоянные: хостинг, юрист/12, команда | B49: =Допущения!B47+Допущения!B49/12+Допущения!B50 | C49: =Допущения!C47+Допущения!C49/12+Допущения!C50 | D49: =Допущения!D47+Допущения!D49/12+Допущения!D50 | E49: ₽/мес
A50: Расходы без LLM | B50: =B45+B46+B47+B48+B49 | C50: =C45+C46+C47+C48+C49 | D50: =D45+D46+D47+D48+D49 | E50: ₽/мес
A51: Результат
A52: Прибыль при API, ₽/мес | B52: =B30-B50-B37 | C52: =C30-C50-C37 | D52: =D30-D50-D37 | E52: ₽/мес | F52: выручка − расходы без LLM − LLM по API
A53: Прибыль на своём железе, ₽/мес | B53: =B30-B50-B39 | C53: =C30-C50-C39 | D53: =D30-D50-D39 | E53: ₽/мес | F53: выручка − расходы без LLM − GPU и MLOps
A54: Прибыль на своём железе, Lightning, ₽/мес | B54: =B30-B50-B41 | C54: =C30-C50-C41 | D54: =D30-D50-D41 | E54: ₽/мес | F54: выручка − расходы без LLM − GPU и MLOps (Lightning)
A55: Выгоднее | B55: =IF(AND(B52>=B53,B52>=B54),"API",IF(B53>=B54,"Qwen (своё железо)","Lightning (своё железо)")) | C55: =IF(AND(C52>=C53,C52>=C54),"API",IF(C53>=C54,"Qwen (своё железо)","Lightning (своё железо)")) | D55: =IF(AND(D52>=D53,D52>=D54),"API",IF(D53>=D54,"Qwen (своё железо)","Lightning (своё железо)")) | F55: по прибыли; качество моделей разное, см. тест сценариев
A56: Рентабельность при API | B56: =IF(B30=0,0,B52/B30) | C56: =IF(C30=0,0,C52/C30) | D56: =IF(D30=0,0,D52/D30) | E56: %
A57: Рентабельность на своём железе | B57: =IF(B30=0,0,B53/B30) | C57: =IF(C30=0,0,C53/C30) | D57: =IF(D30=0,0,D53/D30) | E57: %
A58: Юнит-экономика на одного платящего
A59: ARPPU, ₽/мес | B59: =B30/B22 | C59: =C30/C22 | D59: =D30/D22 | E59: ₽/мес | F59: выручка ÷ платящие (смесь сегментов)
A60: Переменные расходы при API | B60: =(B37+B45+B46+B47+B48)/B22 | C60: =(C37+C45+C46+C47+C48)/C22 | D60: =(D37+D45+D46+D47+D48)/D22 | E60: ₽/мес | F60: LLM (вкл. бесплатных) + инфраструктура + привлечение + комиссия + налог
A61: Переменные расходы на своём железе | B61: =(B38*Допущения!B39+B45+B46+B47+B48)/B22 | C61: =(C38*Допущения!C39+C45+C46+C47+C48)/C22 | D61: =(D38*Допущения!D39+D45+D46+D47+D48)/D22 | E61: ₽/мес | F61: GPU вместо LLM по API
A62: Вклад платящего при API | B62: =B59-B60 | C62: =C59-C60 | D62: =D59-D60 | E62: ₽/мес
A63: Вклад платящего на своём железе | B63: =B59-B61 | C63: =C59-C61 | D63: =D59-D61 | E63: ₽/мес
A64: Безубыточность при API: платящих | B64: =IF(B62<=0,"нет",B49/B62) | C64: =IF(C62<=0,"нет",C49/C62) | D64: =IF(D62<=0,"нет",D49/D62) | E64: чел. | F64: постоянные ÷ вклад
A65: Безубыточность на своём железе: платящих | B65: =IF(B63<=0,"нет",(B49+Допущения!B45)/B63) | C65: =IF(C63<=0,"нет",(C49+Допущения!C45)/C63) | D65: =IF(D63<=0,"нет",(D49+Допущения!D45)/D63) | E65: чел. | F65: (постоянные + MLOps) ÷ вклад

Sheet Метрики
A1: Ключевые метрики продукта и целевые значения
A3: Метрика | B3: Как измеряем | C3: Целевое значение | D3: Этап / метод (docs/05-discovery.md)
A4: Спрос: CTR кнопки «Подключить почту» | B4: клики ÷ показы лендинга | C4: ≥ 8% | D4: Fake door
A5: Спрос: заявки от кликнувших | B5: оставили контакт ÷ кликнули | C5: ≥ 30% | D5: Fake door
A6: Готовность подключить ящик (заявленная) | B6: ответы «скорее да/да» ÷ все | C6: ≥ 40% (в модели факт. подключение 2–10%: заявленное всегда выше) | D6: Опрос
A7: Готовность платить | B7: доля, готовая платить ≥ 149 ₽/мес | C7: ≥ 25% | D7: Опрос
A8: Боль подтверждена | B8: называют конкретный случай за 3 мес. | C8: ≥ 60% | D8: Интервью
A9: Понятность без подсказки | B9: понимают, что бот делает и чего нет | C9: ≥ 70% | D9: Прототип
A10: Полезность ответов | B10: доля «полезно» в тестовых сценариях | C10: ≥ 80% | D10: Тест сценариев
A11: Критичные ошибки | B11: пропущено важное письмо / выдумка | C11: единицы на прогон | D11: Тест сценариев
A12: Подключение: конверсия онбординга | B12: завершили OAuth ÷ начали | C12: ≥ 50% | D12: Пилот
A13: Активация | B13: сделали ≥ 1 запрос за 24 ч после подключения | C13: ≥ 60% | D13: Пилот
A14: Удержание D14 | B14: вернулись на 2-й неделе | C14: ≥ 50% | D14: Пилот
... A21: Безопасность | B21: инциденты утечки/автоотправки | C21: 0 | D21: Постоянно
